os_shell/__init__.py
os_shell/completer.py
os_shell/lexer.py
os_shell/main.py
os_shell/os_commandhelper.py
os_shell/resources.py
os_shell/style.py
os_shell/toolbar.py
os_shell-1.0.3.dist-info/DESCRIPTION.rst
os_shell-1.0.3.dist-info/entry_points.txt
os_shell-1.0.3.dist-info/METADATA
os_shell-1.0.3.dist-info/metadata.json
os_shell-1.0.3.dist-info/RECORD
os_shell-1.0.3.dist-info/top_level.txt
os_shell-1.0.3.dist-info/WHEEL
