Metadata-Version: 2.0
Name: os-shell
Version: 1.0.3
Summary: An interactive Command Line Shell for Openstack CLI
Home-page: https://github.com/bdastur/os-shell
Author: Behzad Dastur
Author-email: bdastur@gmail.com
License: MIT
Keywords: openstack cli autocomplete syntax
Platform: UNKNOWN
Requires-Dist: python-openstackclient
Requires-Dist: openstacksdk
Requires-Dist: prompt-toolkit
Requires-Dist: PyYAML
Requires-Dist: Pygments
